lrservice/__init__.py
lrservice/benchmark.py
lrservice/main.py
lrservice/simple_linear_regr.py
lrservice/simple_linear_regr_utils.py
lrservice/tests/__init__.py
lrservice/tests/test_simple_linear_regr.py
lrservice-0.0.5.dist-info/LICENSE
lrservice-0.0.5.dist-info/METADATA
lrservice-0.0.5.dist-info/WHEEL
lrservice-0.0.5.dist-info/top_level.txt
lrservice-0.0.5.dist-info/RECORD
